__init__.py
dmc/DunedinPACE.py
dmc/__init__.py
dmc/_version.py
dmc/cgID.py
dmc/clock_info.py
dmc/helpdoc.py
dmc/imputation.py
dmc/ireader.py
dmc/methylclocks.py
dmc/methyldat.py
dmc/tf_mse.py
dmc/utils.py
dmc/data/AltumAge.h5
dmc/data/AltumAge.pkl
dmc/data/Cortical.pkl
dmc/data/DunedinPACE.pkl
dmc/data/ENCen100.pkl
dmc/data/ENCen40.pkl
dmc/data/GA_Bohlin.pkl
dmc/data/GA_Haftorn.pkl
dmc/data/GA_Knight.pkl
dmc/data/GA_Lee_CPC.pkl
dmc/data/GA_Lee_RPC.pkl
dmc/data/GA_Lee_rRPC.pkl
dmc/data/GA_Mayne.pkl
dmc/data/Hannum.pkl
dmc/data/Horvath13.pkl
dmc/data/Horvath13_shrunk.pkl
dmc/data/Horvath18.pkl
dmc/data/Levine.pkl
dmc/data/Lin.pkl
dmc/data/Lu_DNAmTL.pkl
dmc/data/MEAT.pkl
dmc/data/PedBE.pkl
dmc/data/Ped_Wu.pkl
dmc/data/WLMT_mm10.pkl
dmc/data/WLMT_mm39.pkl
dmc/data/Weidner.pkl
dmc/data/YOMT_mm10.pkl
dmc/data/YOMT_mm39.pkl
dmc/data/Zhang_BLUP.pkl
dmc/data/Zhang_EN.pkl
dmc/data/__init__.py
dmc/data/mmBlood_mm10.pkl
dmc/data/mmBlood_mm39.pkl
dmc/data/mmLiver_mm10.pkl
dmc/data/mmLiver_mm39.pkl
dmc/data/multi_platform_cpgs.pkl
dmc/data/scaler.pkl
epical-1.3.0.dist-info/LICENSE
epical-1.3.0.dist-info/METADATA
epical-1.3.0.dist-info/WHEEL
epical-1.3.0.dist-info/entry_points.txt
epical-1.3.0.dist-info/top_level.txt
epical-1.3.0.dist-info/RECORD
