Metadata-Version: 2.2
Name: epical
Version: 1.3.0
Summary: epical --- Epigenetic age Calculator
Author-email: Liguo Wang <wangliguo78@gmail.com>
Maintainer-email: Liguo Wang <wangliguo78@gmail.com>
License: Copyright (c) 2024 The Python Packaging Authority
Project-URL: Documentation, https://epical.readthedocs.io/en/latest/
Project-URL: Repository, https://github.com/liguowang/epical.git
Project-URL: Issues, https://github.com/liguowang/epical/issues
Project-URL: TestData, https://sourceforge.net/projects/epical/files/
Keywords: epigenetics age,biological age,DNA methylation,MethylationEPIC,850K,450K,RRBS,WGBS
Classifier: Programming Language :: Python :: 3
Classifier: Development Status :: 4 - Beta
Classifier: License :: OSI Approved :: MIT License
Classifier: Environment :: Console
Classifier: Intended Audience :: Science/Research
Classifier: Operating System :: MacOS :: MacOS X
Classifier: Operating System :: POSIX
Classifier: Topic :: Scientific/Engineering :: Bio-Informatics
Requires-Python: >=3.8
License-File: LICENSE
Requires-Dist: numpy
Requires-Dist: scipy
Requires-Dist: scikit-learn
Requires-Dist: bx-python
Requires-Dist: pandas
Requires-Dist: EpigeneticPacemaker
Requires-Dist: matplotlib
Requires-Dist: tensorflow
Requires-Dist: rpy2
